setup.py
pimpleDyMFlux/__init__.py
pimpleDyMFlux.egg-info/PKG-INFO
pimpleDyMFlux.egg-info/SOURCES.txt
pimpleDyMFlux.egg-info/dependency_links.txt
pimpleDyMFlux.egg-info/entry_points.txt
pimpleDyMFlux.egg-info/requires.txt
pimpleDyMFlux.egg-info/top_level.txt
pimpleDyMFlux.egg-info/zip-safe
pimpleDyMFlux/r1_6/__init__.py
pimpleDyMFlux/r1_6_dev/__init__.py
pimpleDyMFlux/r1_7_0/__init__.py
pimpleDyMFlux/r2_0_0/__init__.py
pimpleDyMFlux/r2_1_0/__init__.py
pimpleDyMFlux/r2_1_1/__init__.py